[
  {
    "id": "tower-of-god",
    "title": "Tower of God",
    "title_kr": "신의 탑",
    "anilist_id": 105778,
    "platform": "webtoon",
    "platform_label": "WEBTOON",
    "read_url": "https://www.webtoons.com/en/fantasy/tower-of-god/list?title_no=95",
    "update_day": 1,
    "update_day_name": "Monday",
    "release_hour_kst": 0,
    "on_hiatus": true,
    "genre": "Fantasy",
    "tags": [
      "action",
      "fantasy",
      "adventure",
      "korean"
    ],
    "amazon_vol1": "https://www.amazon.com/dp/1990259766?tag=YOUR_TAG",
    "seo_description": "Tower of God drops every Monday at midnight KST on WEBTOON. Live countdown to the next episode. Never miss a release.",
    "platforms": [
      {
        "platform": "webtoon",
        "label": "WEBTOON",
        "read_url": "https://www.webtoons.com/en/fantasy/tower-of-god/list?title_no=95"
      }
    ]
  },
  {
    "id": "omniscient-readers-viewpoint",
    "title": "Omniscient Reader's Viewpoint",
    "title_kr": "전지적 독자 시점",
    "anilist_id": 130136,
    "platform": "webtoon",
    "platform_label": "WEBTOON",
    "read_url": "https://www.webtoons.com/en/action/omniscient-reader/list?title_no=2154",
    "update_day": 2,
    "update_day_name": "Tuesday",
    "release_hour_kst": 0,
    "on_hiatus": false,
    "genre": "Action",
    "tags": [
      "action",
      "apocalypse",
      "fantasy",
      "korean"
    ],
    "amazon_vol1": "https://www.amazon.com/s?k=omniscient+reader+viewpoint+manga&tag=YOUR_TAG",
    "seo_description": "Omniscient Reader's Viewpoint drops every Tuesday at midnight KST on WEBTOON. Live countdown to the next chapter release.",
    "platforms": [
      {
        "platform": "webtoon",
        "label": "WEBTOON",
        "read_url": "https://www.webtoons.com/en/action/omniscient-reader/list?title_no=2154"
      }
    ]
  },
  {
    "id": "eleceed",
    "title": "Eleceed",
    "title_kr": "엘리시드",
    "anilist_id": 107441,
    "platform": "webtoon",
    "platform_label": "WEBTOON",
    "read_url": "https://www.webtoons.com/en/action/eleceed/list?title_no=1571",
    "update_day": 3,
    "update_day_name": "Wednesday",
    "release_hour_kst": 0,
    "on_hiatus": false,
    "genre": "Action",
    "tags": [
      "action",
      "supernatural",
      "comedy",
      "korean"
    ],
    "amazon_vol1": "https://www.amazon.com/s?k=eleceed+manga&tag=YOUR_TAG",
    "seo_description": "Eleceed drops every Wednesday at midnight KST on WEBTOON. See the live countdown to the next episode.",
    "platforms": [
      {
        "platform": "webtoon",
        "label": "WEBTOON",
        "read_url": "https://www.webtoons.com/en/action/eleceed/list?title_no=1571"
      }
    ]
  },
  {
    "id": "nano-machine",
    "title": "Nano Machine",
    "title_kr": "나노 마신",
    "anilist_id": 114148,
    "platform": "webtoon",
    "platform_label": "WEBTOON",
    "read_url": "https://www.webtoons.com/en/action/nano-machine/list?title_no=2202",
    "update_day": 4,
    "update_day_name": "Thursday",
    "release_hour_kst": 0,
    "on_hiatus": false,
    "genre": "Martial Arts",
    "tags": [
      "martial arts",
      "fantasy",
      "action",
      "korean"
    ],
    "amazon_vol1": "https://www.amazon.com/s?k=nano+machine+manhwa&tag=YOUR_TAG",
    "seo_description": "Nano Machine drops every Thursday at midnight KST on WEBTOON. Live countdown to the next episode release.",
    "platforms": [
      {
        "platform": "webtoon",
        "label": "WEBTOON",
        "read_url": "https://www.webtoons.com/en/action/nano-machine/list?title_no=2202"
      }
    ]
  },
  {
    "id": "mercenary-enrollment",
    "title": "Mercenary Enrollment",
    "title_kr": "용병으로 살아남기",
    "anilist_id": 132052,
    "platform": "webtoon",
    "platform_label": "WEBTOON",
    "read_url": "https://www.webtoons.com/en/action/mercenary-enrollment/list?title_no=2304",
    "update_day": 5,
    "update_day_name": "Friday",
    "release_hour_kst": 0,
    "on_hiatus": false,
    "genre": "Action",
    "tags": [
      "action",
      "school",
      "fighting",
      "korean"
    ],
    "amazon_vol1": "https://www.amazon.com/s?k=mercenary+enrollment+manhwa&tag=YOUR_TAG",
    "seo_description": "Mercenary Enrollment drops every Friday at midnight KST on WEBTOON. Live countdown to the next episode.",
    "platforms": [
      {
        "platform": "webtoon",
        "label": "WEBTOON",
        "read_url": "https://www.webtoons.com/en/action/mercenary-enrollment/list?title_no=2304"
      }
    ]
  },
  {
    "id": "the-beginning-after-the-end",
    "title": "The Beginning After the End",
    "title_kr": "The Beginning After the End",
    "anilist_id": 104652,
    "platform": "tapas",
    "platform_label": "TAPAS",
    "read_url": "https://tapas.io/series/tbate-comic/info",
    "update_day": 6,
    "update_day_name": "Saturday",
    "release_hour_kst": 0,
    "on_hiatus": false,
    "genre": "Fantasy",
    "tags": [
      "fantasy",
      "isekai",
      "action",
      "reincarnation"
    ],
    "amazon_vol1": "https://www.amazon.com/s?k=the+beginning+after+the+end+manhwa&tag=YOUR_TAG",
    "seo_description": "The Beginning After the End drops every Saturday on Tapas. Live countdown to the next episode.",
    "platforms": [
      {
        "platform": "tapas",
        "label": "TAPAS",
        "read_url": "https://tapas.io/series/tbate-comic/info"
      }
    ]
  },
  {
    "id": "reaper-of-the-drifting-moon",
    "title": "Reaper of the Drifting Moon",
    "title_kr": "방랑의 달 리퍼",
    "anilist_id": 158396,
    "platform": "webtoon",
    "platform_label": "WEBTOON",
    "read_url": "https://www.webtoons.com/en/action/reaper-of-the-drifting-moon/list?title_no=2306",
    "update_day": 0,
    "update_day_name": "Sunday",
    "release_hour_kst": 0,
    "on_hiatus": false,
    "genre": "Fantasy",
    "tags": [
      "fantasy",
      "martial arts",
      "action",
      "korean"
    ],
    "amazon_vol1": "https://www.amazon.com/s?k=reaper+drifting+moon+manhwa&tag=YOUR_TAG",
    "seo_description": "Reaper of the Drifting Moon drops every Sunday at midnight KST on WEBTOON. Live countdown to the next episode.",
    "platforms": [
      {
        "platform": "webtoon",
        "label": "WEBTOON",
        "read_url": "https://www.webtoons.com/en/action/reaper-of-the-drifting-moon/list?title_no=2306"
      }
    ]
  },
  {
    "id": "i-love-yoo",
    "title": "I Love Yoo",
    "title_kr": "I Love Yoo",
    "anilist_id": 98938,
    "platform": "webtoon",
    "platform_label": "WEBTOON",
    "read_url": "https://www.webtoons.com/en/romance/i-love-yoo/list?title_no=986",
    "update_day": 1,
    "update_day_name": "Monday",
    "release_hour_kst": 0,
    "on_hiatus": false,
    "genre": "Romance",
    "tags": [
      "romance",
      "drama",
      "slice of life"
    ],
    "amazon_vol1": null,
    "seo_description": "I Love Yoo drops every Monday at midnight KST on WEBTOON. Live countdown to the next chapter.",
    "platforms": [
      {
        "platform": "webtoon",
        "label": "WEBTOON",
        "read_url": "https://www.webtoons.com/en/romance/i-love-yoo/list?title_no=986"
      }
    ]
  },
  {
    "id": "unordinary",
    "title": "unOrdinary",
    "title_kr": "unOrdinary",
    "anilist_id": 87600,
    "platform": "webtoon",
    "platform_label": "WEBTOON",
    "read_url": "https://www.webtoons.com/en/super-hero/unordinary/list?title_no=679",
    "update_day": 3,
    "update_day_name": "Wednesday",
    "release_hour_kst": 0,
    "on_hiatus": false,
    "genre": "Action",
    "tags": [
      "action",
      "superpower",
      "school",
      "drama"
    ],
    "amazon_vol1": "https://www.amazon.com/s?k=unordinary+webtoon+book&tag=YOUR_TAG",
    "seo_description": "unOrdinary drops every Wednesday at midnight KST on WEBTOON. Live countdown to the next episode.",
    "platforms": [
      {
        "platform": "webtoon",
        "label": "WEBTOON",
        "read_url": "https://www.webtoons.com/en/super-hero/unordinary/list?title_no=679"
      }
    ]
  },
  {
    "id": "lore-olympus",
    "title": "Lore Olympus",
    "title_kr": "Lore Olympus",
    "anilist_id": 101471,
    "platform": "webtoon",
    "platform_label": "WEBTOON",
    "read_url": "https://www.webtoons.com/en/romance/lore-olympus/list?title_no=1320",
    "update_day": 0,
    "update_day_name": "Sunday",
    "release_hour_kst": 0,
    "on_hiatus": true,
    "genre": "Romance",
    "tags": [
      "romance",
      "mythology",
      "drama",
      "fantasy"
    ],
    "amazon_vol1": "https://www.amazon.com/s?k=lore+olympus+book&tag=YOUR_TAG",
    "seo_description": "Lore Olympus release schedule and next episode countdown on WEBTOON. Check the latest episode release date.",
    "platforms": [
      {
        "platform": "webtoon",
        "label": "WEBTOON",
        "read_url": "https://www.webtoons.com/en/romance/lore-olympus/list?title_no=1320"
      }
    ]
  },
  {
    "id": "true-beauty",
    "title": "True Beauty",
    "title_kr": "여신강림",
    "anilist_id": 101562,
    "platform": "webtoon",
    "platform_label": "WEBTOON",
    "read_url": "https://www.webtoons.com/en/romance/truebeauty/list?title_no=1436",
    "update_day": 4,
    "update_day_name": "Thursday",
    "release_hour_kst": 0,
    "on_hiatus": false,
    "genre": "Romance",
    "tags": [
      "romance",
      "drama",
      "slice of life",
      "korean"
    ],
    "amazon_vol1": "https://www.amazon.com/s?k=true+beauty+manhwa&tag=YOUR_TAG",
    "seo_description": "True Beauty drops every Thursday on WEBTOON. Live countdown to the next episode of 여신강림.",
    "platforms": [
      {
        "platform": "webtoon",
        "label": "WEBTOON",
        "read_url": "https://www.webtoons.com/en/romance/truebeauty/list?title_no=1436"
      }
    ]
  },
  {
    "id": "subzero",
    "title": "SubZero",
    "title_kr": "SubZero",
    "anilist_id": 103039,
    "platform": "webtoon",
    "platform_label": "WEBTOON",
    "read_url": "https://www.webtoons.com/en/romance/subzero/list?title_no=1468",
    "update_day": 2,
    "update_day_name": "Tuesday",
    "release_hour_kst": 0,
    "on_hiatus": false,
    "genre": "Romance",
    "tags": [
      "romance",
      "fantasy",
      "dragons",
      "drama"
    ],
    "amazon_vol1": "https://www.amazon.com/s?k=subzero+webtoon+book&tag=YOUR_TAG",
    "seo_description": "SubZero drops every Tuesday at midnight KST on WEBTOON. Live countdown to the next chapter.",
    "platforms": [
      {
        "platform": "webtoon",
        "label": "WEBTOON",
        "read_url": "https://www.webtoons.com/en/romance/subzero/list?title_no=1468"
      }
    ]
  },
  {
    "id": "lets-play",
    "title": "Let's Play",
    "title_kr": "Let's Play",
    "anilist_id": 98835,
    "platform": "webtoon",
    "platform_label": "WEBTOON",
    "read_url": "https://www.webtoons.com/en/romance/letsplay/list?title_no=1218",
    "update_day": 5,
    "update_day_name": "Friday",
    "release_hour_kst": 0,
    "on_hiatus": false,
    "genre": "Romance",
    "tags": [
      "romance",
      "comedy",
      "gaming",
      "slice of life"
    ],
    "amazon_vol1": "https://www.amazon.com/s?k=lets+play+webtoon+book&tag=YOUR_TAG",
    "seo_description": "Let's Play drops every Friday at midnight KST on WEBTOON. Live countdown to the next episode.",
    "platforms": [
      {
        "platform": "webtoon",
        "label": "WEBTOON",
        "read_url": "https://www.webtoons.com/en/romance/letsplay/list?title_no=1218"
      }
    ]
  },
  {
    "id": "jungle-juice",
    "title": "Jungle Juice",
    "title_kr": "정글쥬스",
    "anilist_id": 132429,
    "platform": "webtoon",
    "platform_label": "WEBTOON",
    "read_url": "https://www.webtoons.com/en/action/jungle-juice/list?title_no=2535",
    "update_day": 3,
    "update_day_name": "Wednesday",
    "release_hour_kst": 0,
    "on_hiatus": false,
    "genre": "Action",
    "tags": [
      "action",
      "supernatural",
      "insect",
      "korean"
    ],
    "amazon_vol1": "https://www.amazon.com/s?k=jungle+juice+manhwa&tag=YOUR_TAG",
    "seo_description": "Jungle Juice drops every Wednesday at midnight KST on WEBTOON. Live countdown to the next episode.",
    "platforms": [
      {
        "platform": "webtoon",
        "label": "WEBTOON",
        "read_url": "https://www.webtoons.com/en/action/jungle-juice/list?title_no=2535"
      }
    ]
  },
  {
    "id": "doom-breaker",
    "title": "Doom Breaker",
    "title_kr": "둠 브레이커",
    "anilist_id": null,
    "platform": "webtoon",
    "platform_label": "WEBTOON",
    "read_url": "https://www.webtoons.com/en/fantasy/doom-breaker/list?title_no=3637",
    "update_day": 6,
    "update_day_name": "Saturday",
    "release_hour_kst": 0,
    "on_hiatus": false,
    "genre": "Fantasy",
    "tags": [
      "fantasy",
      "action",
      "time travel",
      "korean"
    ],
    "amazon_vol1": null,
    "seo_description": "Doom Breaker drops every Saturday at midnight KST on WEBTOON. Live countdown to the next chapter release.",
    "platforms": [
      {
        "platform": "webtoon",
        "label": "WEBTOON",
        "read_url": "https://www.webtoons.com/en/fantasy/doom-breaker/list?title_no=3637"
      }
    ]
  },
  {
    "id": "solo-leveling-ragnarok",
    "title": "Solo Leveling: Ragnarok",
    "title_kr": "Solo Leveling: Ragnarok",
    "anilist_id": 166840,
    "platform": "tapas",
    "platform_label": "TAPAS",
    "read_url": "https://tapas.io/series/solo-leveling-ragnarok/info",
    "update_day": 4,
    "update_day_name": "Thursday",
    "release_hour_kst": 0,
    "on_hiatus": false,
    "genre": "Action",
    "tags": [
      "action",
      "fantasy",
      "overpowered",
      "korean"
    ],
    "amazon_vol1": "https://www.amazon.com/s?k=solo+leveling+ragnarok+manhwa&tag=YOUR_TAG",
    "seo_description": "Solo Leveling: Ragnarok drops every Thursday on Tapas. Live countdown to the next chapter release.",
    "platforms": [
      {
        "platform": "tapas",
        "label": "TAPAS",
        "read_url": "https://tapas.io/series/solo-leveling-ragnarok/info"
      }
    ]
  },
  {
    "id": "second-life-ranker",
    "title": "Second Life Ranker",
    "title_kr": "랭커의 귀환",
    "anilist_id": null,
    "platform": "webtoon",
    "platform_label": "WEBTOON",
    "read_url": "https://www.webtoons.com/en/fantasy/second-life-ranker/list?title_no=1966",
    "update_day": 6,
    "update_day_name": "Saturday",
    "release_hour_kst": 0,
    "on_hiatus": false,
    "genre": "Fantasy",
    "tags": [
      "fantasy",
      "action",
      "regression"
    ],
    "amazon_vol1": null,
    "seo_description": "Second Life Ranker drops every Saturday on WEBTOON. Live countdown to the next chapter.",
    "platforms": [
      {
        "platform": "webtoon",
        "label": "WEBTOON",
        "read_url": "https://www.webtoons.com/en/fantasy/second-life-ranker/list?title_no=1966"
      }
    ]
  },
  {
    "id": "overgeared",
    "title": "Overgeared",
    "title_kr": "오버기어드",
    "anilist_id": null,
    "platform": "webtoon",
    "platform_label": "WEBTOON",
    "read_url": "https://www.webtoons.com/en/fantasy/overgeared/list?title_no=2057",
    "update_day": 0,
    "update_day_name": "Sunday",
    "release_hour_kst": 0,
    "on_hiatus": false,
    "genre": "Fantasy",
    "tags": [
      "fantasy",
      "action",
      "game"
    ],
    "amazon_vol1": null,
    "seo_description": "Overgeared updates every Sunday on WEBTOON. Live countdown.",
    "platforms": [
      {
        "platform": "webtoon",
        "label": "WEBTOON",
        "read_url": "https://www.webtoons.com/en/fantasy/overgeared/list?title_no=2057"
      }
    ]
  },
  {
    "id": "kill-the-hero",
    "title": "Kill the Hero",
    "title_kr": "영웅을 죽여라",
    "anilist_id": null,
    "platform": "webtoon",
    "platform_label": "WEBTOON",
    "read_url": "https://www.webtoons.com/en/fantasy/kill-the-hero/list?title_no=1948",
    "update_day": 1,
    "update_day_name": "Monday",
    "release_hour_kst": 0,
    "on_hiatus": false,
    "genre": "Fantasy",
    "tags": [
      "fantasy",
      "action",
      "regression"
    ],
    "amazon_vol1": null,
    "seo_description": "Kill the Hero drops every Monday on WEBTOON. Countdown to the next episode.",
    "platforms": [
      {
        "platform": "webtoon",
        "label": "WEBTOON",
        "read_url": "https://www.webtoons.com/en/fantasy/kill-the-hero/list?title_no=1948"
      }
    ]
  },
  {
    "id": "return-of-the-mount-hua-sect",
    "title": "Return of the Mount Hua Sect",
    "title_kr": "화산귀환",
    "anilist_id": 145514,
    "platform": "webtoon",
    "platform_label": "WEBTOON",
    "read_url": "https://www.webtoons.com/en/action/return-of-the-mount-hua-sect/list?title_no=3892",
    "update_day": 6,
    "update_day_name": "Saturday",
    "release_hour_kst": 0,
    "on_hiatus": false,
    "genre": "Martial Arts",
    "tags": [
      "action",
      "martial-arts",
      "regression",
      "historical"
    ],
    "amazon_vol1": null,
    "seo_description": "Return of the Mount Hua Sect drops every Saturday on WEBTOON.",
    "platforms": [
      {
        "platform": "webtoon",
        "label": "WEBTOON",
        "read_url": "https://www.webtoons.com/en/action/return-of-the-mount-hua-sect/list?title_no=3892"
      }
    ]
  },
  {
    "id": "murim-login",
    "title": "Murim Login",
    "title_kr": "무림 로그인",
    "anilist_id": null,
    "platform": "webtoon",
    "platform_label": "WEBTOON",
    "read_url": "https://www.webtoons.com/en/action/murim-login/list?title_no=2676",
    "update_day": 0,
    "update_day_name": "Sunday",
    "release_hour_kst": 0,
    "on_hiatus": false,
    "genre": "Martial Arts",
    "tags": [
      "action",
      "martial-arts",
      "game"
    ],
    "amazon_vol1": null,
    "seo_description": "Murim Login drops every Sunday on WEBTOON. Live countdown.",
    "platforms": [
      {
        "platform": "webtoon",
        "label": "WEBTOON",
        "read_url": "https://www.webtoons.com/en/action/murim-login/list?title_no=2676"
      }
    ]
  },
  {
    "id": "teenage-mercenary",
    "title": "Teenage Mercenary",
    "title_kr": "용병으로 살아남기",
    "anilist_id": 130189,
    "platform": "webtoon",
    "platform_label": "WEBTOON",
    "read_url": "https://www.webtoons.com/en/action/teenage-mercenary/list?title_no=2116",
    "update_day": 5,
    "update_day_name": "Friday",
    "release_hour_kst": 0,
    "on_hiatus": false,
    "genre": "Action",
    "tags": [
      "action",
      "school",
      "thriller"
    ],
    "amazon_vol1": null,
    "seo_description": "Teenage Mercenary drops every Friday on WEBTOON. Countdown.",
    "platforms": [
      {
        "platform": "webtoon",
        "label": "WEBTOON",
        "read_url": "https://www.webtoons.com/en/action/teenage-mercenary/list?title_no=2116"
      }
    ]
  },
  {
    "id": "lookism",
    "title": "Lookism",
    "title_kr": "외모지상주의",
    "anilist_id": 87136,
    "platform": "webtoon",
    "platform_label": "WEBTOON",
    "read_url": "https://www.webtoons.com/en/slice-of-life/lookism/list?title_no=1049",
    "update_day": 6,
    "update_day_name": "Saturday",
    "release_hour_kst": 0,
    "on_hiatus": false,
    "genre": "Drama",
    "tags": [
      "drama",
      "school",
      "action"
    ],
    "amazon_vol1": null,
    "seo_description": "Lookism drops every Saturday on WEBTOON. Countdown.",
    "platforms": [
      {
        "platform": "webtoon",
        "label": "WEBTOON",
        "read_url": "https://www.webtoons.com/en/slice-of-life/lookism/list?title_no=1049"
      }
    ]
  },
  {
    "id": "the-boxer",
    "title": "The Boxer",
    "title_kr": "더 복서",
    "anilist_id": 121496,
    "platform": "webtoon",
    "platform_label": "WEBTOON",
    "read_url": "https://www.webtoons.com/en/sports/the-boxer/list?title_no=2027",
    "update_day": 0,
    "update_day_name": "Sunday",
    "release_hour_kst": 0,
    "on_hiatus": false,
    "genre": "Sports",
    "tags": [
      "sports",
      "action",
      "drama"
    ],
    "amazon_vol1": null,
    "seo_description": "The Boxer drops every Sunday on WEBTOON. Live countdown.",
    "platforms": [
      {
        "platform": "webtoon",
        "label": "WEBTOON",
        "read_url": "https://www.webtoons.com/en/sports/the-boxer/list?title_no=2027"
      }
    ]
  },
  {
    "id": "windbreaker",
    "title": "Windbreaker",
    "title_kr": "윈드브레이커",
    "anilist_id": 105430,
    "platform": "webtoon",
    "platform_label": "WEBTOON",
    "read_url": "https://www.webtoons.com/en/sports/wind-breaker/list?title_no=372",
    "update_day": 0,
    "update_day_name": "Sunday",
    "release_hour_kst": 0,
    "on_hiatus": false,
    "genre": "Sports",
    "tags": [
      "sports",
      "action",
      "school"
    ],
    "amazon_vol1": null,
    "seo_description": "Windbreaker releases every Sunday on WEBTOON. Countdown.",
    "platforms": [
      {
        "platform": "webtoon",
        "label": "WEBTOON",
        "read_url": "https://www.webtoons.com/en/sports/wind-breaker/list?title_no=372"
      }
    ]
  },
  {
    "id": "the-god-of-high-school",
    "title": "The God of High School",
    "title_kr": "갓 오브 하이스쿨",
    "anilist_id": 83275,
    "platform": "webtoon",
    "platform_label": "WEBTOON",
    "read_url": "https://www.webtoons.com/en/action/the-god-of-high-school/list?title_no=66",
    "update_day": 0,
    "update_day_name": "Sunday",
    "release_hour_kst": 0,
    "on_hiatus": false,
    "genre": "Martial Arts",
    "tags": [
      "action",
      "martial-arts",
      "tournament"
    ],
    "amazon_vol1": null,
    "seo_description": "The God of High School releases every Sunday on WEBTOON. Live countdown.",
    "platforms": [
      {
        "platform": "webtoon",
        "label": "WEBTOON",
        "read_url": "https://www.webtoons.com/en/action/the-god-of-high-school/list?title_no=66"
      }
    ]
  },
  {
    "id": "worn-and-torn-newbie",
    "title": "Worn and Torn Newbie",
    "title_kr": "닳고 닳은 뉴비",
    "anilist_id": null,
    "platform": "webtoon",
    "platform_label": "WEBTOON",
    "read_url": "https://www.webtoons.com/en/fantasy/worn-and-torn-newbie/list?title_no=2720",
    "update_day": 2,
    "update_day_name": "Tuesday",
    "release_hour_kst": 0,
    "on_hiatus": false,
    "genre": "Fantasy",
    "tags": [
      "fantasy",
      "action",
      "game"
    ],
    "amazon_vol1": null,
    "seo_description": "Worn and Torn Newbie drops every Tuesday on WEBTOON. Live countdown.",
    "platforms": [
      {
        "platform": "webtoon",
        "label": "WEBTOON",
        "read_url": "https://www.webtoons.com/en/fantasy/worn-and-torn-newbie/list?title_no=2720"
      }
    ]
  },
  {
    "id": "legend-of-the-northern-blade",
    "title": "Legend of the Northern Blade",
    "title_kr": "북검전기",
    "anilist_id": 114980,
    "platform": "webtoon",
    "platform_label": "WEBTOON",
    "read_url": "https://www.webtoons.com/en/action/legend-of-the-northern-blade/list?title_no=1874",
    "update_day": 6,
    "update_day_name": "Saturday",
    "release_hour_kst": 0,
    "on_hiatus": false,
    "genre": "Martial Arts",
    "tags": [
      "action",
      "martial-arts",
      "historical"
    ],
    "amazon_vol1": null,
    "seo_description": "Legend of the Northern Blade drops every Saturday on WEBTOON. Live countdown.",
    "platforms": [
      {
        "platform": "webtoon",
        "label": "WEBTOON",
        "read_url": "https://www.webtoons.com/en/action/legend-of-the-northern-blade/list?title_no=1874"
      }
    ]
  },
  {
    "id": "the-s-classes-that-i-raised",
    "title": "The S-Classes That I Raised",
    "title_kr": "내가 키운 S급들",
    "anilist_id": null,
    "platform": "webtoon",
    "platform_label": "WEBTOON",
    "read_url": "https://www.webtoons.com/en/fantasy/the-s-classes-that-i-raised/list?title_no=2085",
    "update_day": 4,
    "update_day_name": "Thursday",
    "release_hour_kst": 0,
    "on_hiatus": false,
    "genre": "Fantasy",
    "tags": [
      "fantasy",
      "action",
      "regression"
    ],
    "amazon_vol1": null,
    "seo_description": "The S-Classes That I Raised updates every Thursday on WEBTOON.",
    "platforms": [
      {
        "platform": "webtoon",
        "label": "WEBTOON",
        "read_url": "https://www.webtoons.com/en/fantasy/the-s-classes-that-i-raised/list?title_no=2085"
      }
    ]
  },
  {
    "id": "the-tutorial-is-too-hard",
    "title": "The Tutorial Is Too Hard",
    "title_kr": "튜토리얼이 너무 어렵다",
    "anilist_id": null,
    "platform": "webtoon",
    "platform_label": "WEBTOON",
    "read_url": "https://www.webtoons.com/en/fantasy/the-tutorial-is-too-hard/list?title_no=1891",
    "update_day": 5,
    "update_day_name": "Friday",
    "release_hour_kst": 0,
    "on_hiatus": false,
    "genre": "Fantasy",
    "tags": [
      "fantasy",
      "action",
      "game"
    ],
    "amazon_vol1": null,
    "seo_description": "The Tutorial Is Too Hard drops every Friday on WEBTOON. Live countdown.",
    "platforms": [
      {
        "platform": "webtoon",
        "label": "WEBTOON",
        "read_url": "https://www.webtoons.com/en/fantasy/the-tutorial-is-too-hard/list?title_no=1891"
      }
    ]
  },
  {
    "id": "the-live",
    "title": "The Live",
    "title_kr": "더 라이브",
    "anilist_id": null,
    "platform": "webtoon",
    "platform_label": "WEBTOON",
    "read_url": "https://www.webtoons.com/en/fantasy/the-live/list?title_no=2119",
    "update_day": 2,
    "update_day_name": "Tuesday",
    "release_hour_kst": 0,
    "on_hiatus": false,
    "genre": "Fantasy",
    "tags": [
      "fantasy",
      "regression",
      "action"
    ],
    "amazon_vol1": null,
    "seo_description": "The Live updates every Tuesday on WEBTOON. Live countdown.",
    "platforms": [
      {
        "platform": "webtoon",
        "label": "WEBTOON",
        "read_url": "https://www.webtoons.com/en/fantasy/the-live/list?title_no=2119"
      }
    ]
  },
  {
    "id": "remarried-empress",
    "title": "Remarried Empress",
    "title_kr": "재혼황후",
    "anilist_id": 109513,
    "platform": "webtoon",
    "platform_label": "WEBTOON",
    "read_url": "https://www.webtoons.com/en/romance/remarried-empress/list?title_no=2135",
    "update_day": 4,
    "update_day_name": "Thursday",
    "release_hour_kst": 0,
    "on_hiatus": false,
    "genre": "Romance",
    "tags": [
      "romance",
      "fantasy",
      "historical"
    ],
    "amazon_vol1": null,
    "seo_description": "Remarried Empress updates every Thursday on WEBTOON. Live countdown.",
    "platforms": [
      {
        "platform": "webtoon",
        "label": "WEBTOON",
        "read_url": "https://www.webtoons.com/en/romance/remarried-empress/list?title_no=2135"
      }
    ]
  },
  {
    "id": "under-the-oak-tree",
    "title": "Under the Oak Tree",
    "title_kr": "참나무 아래서",
    "anilist_id": null,
    "platform": "tapas",
    "platform_label": "TAPAS",
    "read_url": "https://tapas.io/series/under-the-oak-tree-official/info",
    "update_day": 6,
    "update_day_name": "Saturday",
    "release_hour_kst": 0,
    "on_hiatus": false,
    "genre": "Romance",
    "tags": [
      "romance",
      "fantasy",
      "historical"
    ],
    "amazon_vol1": null,
    "seo_description": "Under the Oak Tree releases every Saturday on Tapas. Countdown.",
    "platforms": [
      {
        "platform": "tapas",
        "label": "TAPAS",
        "read_url": "https://tapas.io/series/under-the-oak-tree-official/info"
      }
    ]
  },
  {
    "id": "who-made-me-a-princess",
    "title": "Who Made Me a Princess",
    "title_kr": "나에게 공주님이 생겼어요",
    "anilist_id": null,
    "platform": "tapas",
    "platform_label": "TAPAS",
    "read_url": "https://tapas.io/series/who-made-me-a-princess/info",
    "update_day": 0,
    "update_day_name": "Sunday",
    "release_hour_kst": 0,
    "on_hiatus": false,
    "genre": "Romance",
    "tags": [
      "romance",
      "fantasy",
      "isekai"
    ],
    "amazon_vol1": null,
    "seo_description": "Who Made Me a Princess releases every Sunday on Tapas. Countdown.",
    "platforms": [
      {
        "platform": "tapas",
        "label": "TAPAS",
        "read_url": "https://tapas.io/series/who-made-me-a-princess/info"
      }
    ]
  },
  {
    "id": "the-villainess-turns-the-hourglass",
    "title": "The Villainess Turns the Hourglass",
    "title_kr": "악녀는 모래시계를 되돌린다",
    "anilist_id": null,
    "platform": "tapas",
    "platform_label": "TAPAS",
    "read_url": "https://tapas.io/series/the-villainess-turns-the-hourglass/info",
    "update_day": 3,
    "update_day_name": "Wednesday",
    "release_hour_kst": 0,
    "on_hiatus": false,
    "genre": "Romance",
    "tags": [
      "romance",
      "fantasy",
      "villainess"
    ],
    "amazon_vol1": null,
    "seo_description": "The Villainess Turns the Hourglass drops every Wednesday on Tapas. Countdown.",
    "platforms": [
      {
        "platform": "tapas",
        "label": "TAPAS",
        "read_url": "https://tapas.io/series/the-villainess-turns-the-hourglass/info"
      }
    ]
  },
  {
    "id": "doctor-elise",
    "title": "Doctor Elise",
    "title_kr": "엘리제가 사랑한 의사",
    "anilist_id": null,
    "platform": "tapas",
    "platform_label": "TAPAS",
    "read_url": "https://tapas.io/series/doctor-elise/info",
    "update_day": 5,
    "update_day_name": "Friday",
    "release_hour_kst": 0,
    "on_hiatus": false,
    "genre": "Romance",
    "tags": [
      "romance",
      "fantasy",
      "medical"
    ],
    "amazon_vol1": null,
    "seo_description": "Doctor Elise updates every Friday on Tapas. Live countdown.",
    "platforms": [
      {
        "platform": "tapas",
        "label": "TAPAS",
        "read_url": "https://tapas.io/series/doctor-elise/info"
      }
    ]
  },
  {
    "id": "my-gently-raised-beast",
    "title": "My Gently Raised Beast",
    "title_kr": "부드럽게 키운 짐승",
    "anilist_id": null,
    "platform": "tapas",
    "platform_label": "TAPAS",
    "read_url": "https://tapas.io/series/my-gently-raised-beast/info",
    "update_day": 2,
    "update_day_name": "Tuesday",
    "release_hour_kst": 0,
    "on_hiatus": false,
    "genre": "Romance",
    "tags": [
      "romance",
      "fantasy",
      "historical"
    ],
    "amazon_vol1": null,
    "seo_description": "My Gently Raised Beast drops every Tuesday on Tapas. Live countdown.",
    "platforms": [
      {
        "platform": "tapas",
        "label": "TAPAS",
        "read_url": "https://tapas.io/series/my-gently-raised-beast/info"
      }
    ]
  },
  {
    "id": "the-villainess-lives-twice",
    "title": "The Villainess Lives Twice",
    "title_kr": "악녀는 두 번 산다",
    "anilist_id": null,
    "platform": "tapas",
    "platform_label": "TAPAS",
    "read_url": "https://tapas.io/series/the-villainess-lives-twice/info",
    "update_day": 5,
    "update_day_name": "Friday",
    "release_hour_kst": 0,
    "on_hiatus": false,
    "genre": "Romance",
    "tags": [
      "romance",
      "fantasy",
      "villainess"
    ],
    "amazon_vol1": null,
    "seo_description": "The Villainess Lives Twice drops every Friday on Tapas. Countdown.",
    "platforms": [
      {
        "platform": "tapas",
        "label": "TAPAS",
        "read_url": "https://tapas.io/series/the-villainess-lives-twice/info"
      }
    ]
  },
  {
    "id": "noblesse",
    "title": "Noblesse",
    "title_kr": "노블레스",
    "anilist_id": null,
    "platform": "webtoon",
    "platform_label": "WEBTOON",
    "read_url": "https://www.webtoons.com/en/supernatural/noblesse/list?title_no=87",
    "update_day": 4,
    "update_day_name": "Thursday",
    "release_hour_kst": 0,
    "on_hiatus": false,
    "genre": "Action",
    "tags": [
      "action",
      "supernatural",
      "fantasy"
    ],
    "amazon_vol1": null,
    "seo_description": "Noblesse updates every Thursday on WEBTOON. Live countdown.",
    "platforms": [
      {
        "platform": "webtoon",
        "label": "WEBTOON",
        "read_url": "https://www.webtoons.com/en/supernatural/noblesse/list?title_no=87"
      }
    ]
  },
  {
    "id": "magic-emperor",
    "title": "Magic Emperor",
    "title_kr": "마법황제",
    "anilist_id": null,
    "platform": "webtoon",
    "platform_label": "WEBTOON",
    "read_url": "https://www.webtoons.com/en/fantasy/magic-emperor/list?title_no=2282",
    "update_day": 0,
    "update_day_name": "Sunday",
    "release_hour_kst": 0,
    "on_hiatus": false,
    "genre": "Fantasy",
    "tags": [
      "fantasy",
      "action",
      "magic"
    ],
    "amazon_vol1": null,
    "seo_description": "Magic Emperor drops every Sunday on WEBTOON. Countdown to next chapter.",
    "platforms": [
      {
        "platform": "webtoon",
        "label": "WEBTOON",
        "read_url": "https://www.webtoons.com/en/fantasy/magic-emperor/list?title_no=2282"
      }
    ]
  },
  {
    "id": "the-great-mage-returns-after-4000-years",
    "title": "The Great Mage Returns After 4000 Years",
    "title_kr": "4000년 만에 귀환한 대마법사",
    "anilist_id": null,
    "platform": "webtoon",
    "platform_label": "WEBTOON",
    "read_url": "https://www.webtoons.com/en/fantasy/the-great-mage-returns-after-4000-years/list?title_no=1963",
    "update_day": 4,
    "update_day_name": "Thursday",
    "release_hour_kst": 0,
    "on_hiatus": false,
    "genre": "Fantasy",
    "tags": [
      "fantasy",
      "action",
      "magic"
    ],
    "amazon_vol1": null,
    "seo_description": "The Great Mage Returns After 4000 Years updates every Thursday on WEBTOON.",
    "platforms": [
      {
        "platform": "webtoon",
        "label": "WEBTOON",
        "read_url": "https://www.webtoons.com/en/fantasy/the-great-mage-returns-after-4000-years/list?title_no=1963"
      }
    ]
  },
  {
    "id": "talent-swallowing-magician",
    "title": "Talent-Swallowing Magician",
    "title_kr": "재능을 삼키는 마법사",
    "anilist_id": null,
    "platform": "webtoon",
    "platform_label": "WEBTOON",
    "read_url": "https://www.webtoons.com/en/fantasy/talent-swallowing-magician/list?title_no=2755",
    "update_day": 5,
    "update_day_name": "Friday",
    "release_hour_kst": 0,
    "on_hiatus": false,
    "genre": "Fantasy",
    "tags": [
      "fantasy",
      "action",
      "magic"
    ],
    "amazon_vol1": null,
    "seo_description": "Talent-Swallowing Magician drops every Friday on WEBTOON. Live countdown.",
    "platforms": [
      {
        "platform": "webtoon",
        "label": "WEBTOON",
        "read_url": "https://www.webtoons.com/en/fantasy/talent-swallowing-magician/list?title_no=2755"
      }
    ]
  },
  {
    "id": "a-returners-magic-should-be-special",
    "title": "A Returner's Magic Should Be Special",
    "title_kr": "귀환자의 마법은 특별해야 합니다",
    "anilist_id": null,
    "platform": "webtoon",
    "platform_label": "WEBTOON",
    "read_url": "https://www.webtoons.com/en/fantasy/a-returners-magic-should-be-special/list?title_no=1697",
    "update_day": 3,
    "update_day_name": "Wednesday",
    "release_hour_kst": 0,
    "on_hiatus": false,
    "genre": "Fantasy",
    "tags": [
      "fantasy",
      "action",
      "regression",
      "magic"
    ],
    "amazon_vol1": null,
    "seo_description": "A Returner's Magic Should Be Special drops every Wednesday on WEBTOON.",
    "platforms": [
      {
        "platform": "webtoon",
        "label": "WEBTOON",
        "read_url": "https://www.webtoons.com/en/fantasy/a-returners-magic-should-be-special/list?title_no=1697"
      }
    ]
  },
  {
    "id": "the-swordmasters-youngest-son",
    "title": "The Swordmaster's Youngest Son",
    "title_kr": "검술명가 막내아들",
    "anilist_id": null,
    "platform": "webtoon",
    "platform_label": "WEBTOON",
    "read_url": "https://www.webtoons.com/en/fantasy/the-swordmasters-youngest-son/list?title_no=4751",
    "update_day": 1,
    "update_day_name": "Monday",
    "release_hour_kst": 0,
    "on_hiatus": false,
    "genre": "Fantasy",
    "tags": [
      "fantasy",
      "action",
      "regression"
    ],
    "amazon_vol1": null,
    "seo_description": "The Swordmaster's Youngest Son drops every Monday on WEBTOON. Countdown.",
    "platforms": [
      {
        "platform": "webtoon",
        "label": "WEBTOON",
        "read_url": "https://www.webtoons.com/en/fantasy/the-swordmasters-youngest-son/list?title_no=4751"
      }
    ]
  },
  {
    "id": "omniscient-reader",
    "title": "Omniscient Reader",
    "title_kr": "전지적 독자 시점",
    "anilist_id": 119257,
    "platform": "webtoon",
    "platform_label": "WEBTOON",
    "read_url": "https://www.webtoons.com/en/action/omniscient-reader/list?title_no=2154",
    "update_day": 2,
    "update_day_name": "Tuesday",
    "release_hour_kst": 10,
    "on_hiatus": false,
    "genre": "Fantasy",
    "tags": [
      "action",
      "adventure",
      "fantasy"
    ],
    "amazon_vol1": null,
    "seo_description": "Omniscient Reader drops every Tuesday on WEBTOON. Live countdown to the next episode.",
    "platforms": [
      {
        "platform": "webtoon",
        "label": "WEBTOON",
        "read_url": "https://www.webtoons.com/en/action/omniscient-reader/list?title_no=2154"
      }
    ]
  },
  {
    "id": "i-m-the-max-level-newbie",
    "title": "I’m the Max-Level Newbie",
    "title_kr": "나 혼자 만렙 뉴비",
    "anilist_id": 137280,
    "platform": "webtoon",
    "platform_label": "WEBTOON",
    "read_url": "https://www.webtoons.com/en/action/im-the-max-level-newbie/list?title_no=3915",
    "update_day": 6,
    "update_day_name": "Saturday",
    "release_hour_kst": 10,
    "on_hiatus": false,
    "genre": "Fantasy",
    "tags": [
      "action",
      "fantasy"
    ],
    "amazon_vol1": null,
    "seo_description": "I’m the Max-Level Newbie drops every Saturday on WEBTOON. Live countdown to the next episode.",
    "platforms": [
      {
        "platform": "webtoon",
        "label": "WEBTOON",
        "read_url": "https://www.webtoons.com/en/action/im-the-max-level-newbie/list?title_no=3915"
      }
    ]
  },
  {
    "id": "the-world-after-the-fall",
    "title": "The World After the Fall",
    "title_kr": "멸망 이후의 세계",
    "anilist_id": 144957,
    "platform": "webtoon",
    "platform_label": "WEBTOON",
    "read_url": "https://www.webtoons.com/en/action/the-world-after-the-fall/list?title_no=4011",
    "update_day": 1,
    "update_day_name": "Monday",
    "release_hour_kst": 10,
    "on_hiatus": false,
    "genre": "Fantasy",
    "tags": [
      "action",
      "adventure",
      "fantasy"
    ],
    "amazon_vol1": null,
    "seo_description": "The World After the Fall drops every Monday on WEBTOON. Live countdown to the next episode.",
    "platforms": [
      {
        "platform": "webtoon",
        "label": "WEBTOON",
        "read_url": "https://www.webtoons.com/en/action/the-world-after-the-fall/list?title_no=4011"
      }
    ]
  },
  {
    "id": "the-return-of-the-disaster-class-hero",
    "title": "The Return of the Disaster-Class Hero",
    "title_kr": "재앙급 영웅님이 귀환하셨다",
    "anilist_id": 143056,
    "platform": "webtoon",
    "platform_label": "WEBTOON",
    "read_url": "https://www.webtoons.com/en/action/the-return-of-the-disaster-class-hero/list?title_no=9013",
    "update_day": 0,
    "update_day_name": "Sunday",
    "release_hour_kst": 11,
    "on_hiatus": false,
    "genre": "Fantasy",
    "tags": [
      "action",
      "fantasy"
    ],
    "amazon_vol1": null,
    "seo_description": "The Return of the Disaster-Class Hero drops every Sunday on WEBTOON. Live countdown to the next episode.",
    "platforms": [
      {
        "platform": "webtoon",
        "label": "WEBTOON",
        "read_url": "https://www.webtoons.com/en/action/the-return-of-the-disaster-class-hero/list?title_no=9013"
      }
    ]
  },
  {
    "id": "the-extra-s-academy-survival-guide",
    "title": "The Extra’s Academy Survival Guide",
    "title_kr": "아카데미에서 살아남기",
    "anilist_id": 172619,
    "platform": "webtoon",
    "platform_label": "WEBTOON",
    "read_url": "https://www.webtoons.com/en/fantasy/the-extras-academy-survival-guide/list?title_no=6465",
    "update_day": 1,
    "update_day_name": "Monday",
    "release_hour_kst": 10,
    "on_hiatus": false,
    "genre": "Fantasy",
    "tags": [
      "action",
      "fantasy"
    ],
    "amazon_vol1": null,
    "seo_description": "The Extra’s Academy Survival Guide drops every Monday on WEBTOON. Live countdown to the next episode.",
    "platforms": [
      {
        "platform": "webtoon",
        "label": "WEBTOON",
        "read_url": "https://www.webtoons.com/en/fantasy/the-extras-academy-survival-guide/list?title_no=6465"
      }
    ]
  },
  {
    "id": "66-666-years-advent-of-the-dark-mage",
    "title": "66,666 Years: Advent of the Dark Mage",
    "title_kr": "66666년만에 환생한 흑마법사",
    "anilist_id": 137595,
    "platform": "webtoon",
    "platform_label": "WEBTOON",
    "read_url": "https://www.webtoons.com/en/fantasy/66666-years-advent-of-the-dark-mage/list?title_no=3441",
    "update_day": 3,
    "update_day_name": "Wednesday",
    "release_hour_kst": 10,
    "on_hiatus": false,
    "genre": "Fantasy",
    "tags": [
      "adventure",
      "fantasy"
    ],
    "amazon_vol1": null,
    "seo_description": "66,666 Years: Advent of the Dark Mage drops every Wednesday on WEBTOON. Live countdown to the next episode.",
    "platforms": [
      {
        "platform": "webtoon",
        "label": "WEBTOON",
        "read_url": "https://www.webtoons.com/en/fantasy/66666-years-advent-of-the-dark-mage/list?title_no=3441"
      }
    ]
  },
  {
    "id": "mythic-item-obtained",
    "title": "Mythic Item Obtained",
    "title_kr": "신화급 귀속 아이템을 손에 넣었다",
    "anilist_id": 151025,
    "platform": "webtoon",
    "platform_label": "WEBTOON",
    "read_url": "https://www.webtoons.com/en/fantasy/mythic-item-obtained/list?title_no=4582",
    "update_day": 4,
    "update_day_name": "Thursday",
    "release_hour_kst": 10,
    "on_hiatus": false,
    "genre": "Fantasy",
    "tags": [
      "action",
      "adventure",
      "fantasy"
    ],
    "amazon_vol1": null,
    "seo_description": "Mythic Item Obtained drops every Thursday on WEBTOON. Live countdown to the next episode.",
    "platforms": [
      {
        "platform": "webtoon",
        "label": "WEBTOON",
        "read_url": "https://www.webtoons.com/en/fantasy/mythic-item-obtained/list?title_no=4582"
      }
    ]
  },
  {
    "id": "the-stellar-swordmaster",
    "title": "The Stellar Swordmaster",
    "title_kr": "별을 품은 소드마스터",
    "anilist_id": 170400,
    "platform": "webtoon",
    "platform_label": "WEBTOON",
    "read_url": "https://www.webtoons.com/en/action/the-stellar-swordmaster/list?title_no=5988",
    "update_day": 3,
    "update_day_name": "Wednesday",
    "release_hour_kst": 10,
    "on_hiatus": false,
    "genre": "Fantasy",
    "tags": [
      "action",
      "adventure",
      "fantasy"
    ],
    "amazon_vol1": null,
    "seo_description": "The Stellar Swordmaster drops every Wednesday on WEBTOON. Live countdown to the next episode.",
    "platforms": [
      {
        "platform": "webtoon",
        "label": "WEBTOON",
        "read_url": "https://www.webtoons.com/en/action/the-stellar-swordmaster/list?title_no=5988"
      }
    ]
  },
  {
    "id": "villain-to-kill",
    "title": "Villain to Kill",
    "title_kr": "빌런투킬",
    "anilist_id": 130149,
    "platform": "webtoon",
    "platform_label": "WEBTOON",
    "read_url": "https://www.webtoons.com/en/action/villain-to-kill/list?title_no=2857",
    "update_day": 2,
    "update_day_name": "Tuesday",
    "release_hour_kst": 10,
    "on_hiatus": false,
    "genre": "Supernatural",
    "tags": [
      "action",
      "supernatural"
    ],
    "amazon_vol1": null,
    "seo_description": "Villain to Kill drops every Tuesday on WEBTOON. Live countdown to the next episode.",
    "platforms": [
      {
        "platform": "webtoon",
        "label": "WEBTOON",
        "read_url": "https://www.webtoons.com/en/action/villain-to-kill/list?title_no=2857"
      }
    ]
  },
  {
    "id": "the-academy-s-undercover-professor",
    "title": "The Academy's Undercover Professor",
    "title_kr": "아카데미에 위장취업당했다",
    "anilist_id": 150836,
    "platform": "webtoon",
    "platform_label": "WEBTOON",
    "read_url": "https://www.webtoons.com/en/fantasy/the-academys-undercover-professor/list?title_no=4636",
    "update_day": 6,
    "update_day_name": "Saturday",
    "release_hour_kst": 11,
    "on_hiatus": false,
    "genre": "Fantasy",
    "tags": [
      "action",
      "adventure",
      "fantasy"
    ],
    "amazon_vol1": null,
    "seo_description": "The Academy's Undercover Professor drops every Saturday on WEBTOON. Live countdown to the next episode.",
    "platforms": [
      {
        "platform": "webtoon",
        "label": "WEBTOON",
        "read_url": "https://www.webtoons.com/en/fantasy/the-academys-undercover-professor/list?title_no=4636"
      }
    ]
  },
  {
    "id": "the-reborn-young-lord-is-an-assassin",
    "title": "The Reborn Young Lord is an Assassin",
    "title_kr": "회귀한 공작가의 막내도련님은 암살자",
    "anilist_id": 175262,
    "platform": "webtoon",
    "platform_label": "WEBTOON",
    "read_url": "https://www.webtoons.com/en/fantasy/the-reborn-young-lord-is-an-assassin/list?title_no=6107",
    "update_day": 1,
    "update_day_name": "Monday",
    "release_hour_kst": 10,
    "on_hiatus": false,
    "genre": "Fantasy",
    "tags": [
      "action",
      "fantasy"
    ],
    "amazon_vol1": null,
    "seo_description": "The Reborn Young Lord is an Assassin drops every Monday on WEBTOON. Live countdown to the next episode.",
    "platforms": [
      {
        "platform": "webtoon",
        "label": "WEBTOON",
        "read_url": "https://www.webtoons.com/en/fantasy/the-reborn-young-lord-is-an-assassin/list?title_no=6107"
      }
    ]
  },
  {
    "id": "the-knight-only-lives-today",
    "title": "The Knight Only Lives Today",
    "title_kr": "오늘만 사는 기사",
    "anilist_id": 177706,
    "platform": "webtoon",
    "platform_label": "WEBTOON",
    "read_url": "https://www.webtoons.com/en/fantasy/the-knight-only-lives-today/list?title_no=6672",
    "update_day": 5,
    "update_day_name": "Friday",
    "release_hour_kst": 11,
    "on_hiatus": false,
    "genre": "Fantasy",
    "tags": [
      "action",
      "fantasy"
    ],
    "amazon_vol1": null,
    "seo_description": "The Knight Only Lives Today drops every Friday on WEBTOON. Live countdown to the next episode.",
    "platforms": [
      {
        "platform": "webtoon",
        "label": "WEBTOON",
        "read_url": "https://www.webtoons.com/en/fantasy/the-knight-only-lives-today/list?title_no=6672"
      }
    ]
  },
  {
    "id": "return-to-player",
    "title": "Return to Player",
    "title_kr": "리턴 투 플레이어",
    "anilist_id": 124577,
    "platform": "webtoon",
    "platform_label": "WEBTOON",
    "read_url": "https://www.webtoons.com/en/action/return-to-player/list?title_no=2574",
    "update_day": 0,
    "update_day_name": "Sunday",
    "release_hour_kst": 11,
    "on_hiatus": false,
    "genre": "Fantasy",
    "tags": [
      "action",
      "adventure",
      "fantasy"
    ],
    "amazon_vol1": null,
    "seo_description": "Return to Player drops every Sunday on WEBTOON. Live countdown to the next episode.",
    "platforms": [
      {
        "platform": "webtoon",
        "label": "WEBTOON",
        "read_url": "https://www.webtoons.com/en/action/return-to-player/list?title_no=2574"
      }
    ]
  },
  {
    "id": "i-killed-the-main-player",
    "title": "I Killed the Main Player",
    "title_kr": "아카데미 플레이어를 죽였다",
    "anilist_id": 173020,
    "platform": "webtoon",
    "platform_label": "WEBTOON",
    "read_url": "https://www.webtoons.com/en/fantasy/i-killed-the-main-player/list?title_no=6856",
    "update_day": 0,
    "update_day_name": "Sunday",
    "release_hour_kst": 11,
    "on_hiatus": false,
    "genre": "Fantasy",
    "tags": [
      "action",
      "fantasy"
    ],
    "amazon_vol1": null,
    "seo_description": "I Killed the Main Player drops every Sunday on WEBTOON. Live countdown to the next episode.",
    "platforms": [
      {
        "platform": "webtoon",
        "label": "WEBTOON",
        "read_url": "https://www.webtoons.com/en/fantasy/i-killed-the-main-player/list?title_no=6856"
      }
    ]
  },
  {
    "id": "descended-from-divinity",
    "title": "Descended from Divinity",
    "title_kr": "천마는 평범하게 살 수 없다",
    "anilist_id": 136204,
    "platform": "webtoon",
    "platform_label": "WEBTOON",
    "read_url": "https://www.webtoons.com/en/fantasy/descended-from-divinity/list?title_no=3450",
    "update_day": 3,
    "update_day_name": "Wednesday",
    "release_hour_kst": 7,
    "on_hiatus": false,
    "genre": "Fantasy",
    "tags": [
      "action",
      "fantasy"
    ],
    "amazon_vol1": null,
    "seo_description": "Descended from Divinity drops every Wednesday on WEBTOON. Live countdown to the next episode.",
    "platforms": [
      {
        "platform": "webtoon",
        "label": "WEBTOON",
        "read_url": "https://www.webtoons.com/en/fantasy/descended-from-divinity/list?title_no=3450"
      }
    ]
  },
  {
    "id": "study-group",
    "title": "Study Group",
    "title_kr": "스터디그룹",
    "anilist_id": 110472,
    "platform": "webtoon",
    "platform_label": "WEBTOON",
    "read_url": "https://www.webtoons.com/en/action/study-group/list?title_no=3595",
    "update_day": 0,
    "update_day_name": "Sunday",
    "release_hour_kst": 11,
    "on_hiatus": false,
    "genre": "Comedy",
    "tags": [
      "action",
      "comedy"
    ],
    "amazon_vol1": null,
    "seo_description": "Study Group drops every Sunday on WEBTOON. Live countdown to the next episode.",
    "platforms": [
      {
        "platform": "webtoon",
        "label": "WEBTOON",
        "read_url": "https://www.webtoons.com/en/action/study-group/list?title_no=3595"
      }
    ]
  },
  {
    "id": "the-regressed-mercenary-has-a-plan",
    "title": "The Regressed Mercenary Has a Plan",
    "title_kr": "회귀한 용병은 다 계획이 있다",
    "anilist_id": 182066,
    "platform": "webtoon",
    "platform_label": "WEBTOON",
    "read_url": "https://www.webtoons.com/en/action/the-regressed-mercenary-has-a-plan/list?title_no=7261",
    "update_day": 3,
    "update_day_name": "Wednesday",
    "release_hour_kst": 10,
    "on_hiatus": false,
    "genre": "Fantasy",
    "tags": [
      "action",
      "fantasy"
    ],
    "amazon_vol1": null,
    "seo_description": "The Regressed Mercenary Has a Plan drops every Wednesday on WEBTOON. Live countdown to the next episode.",
    "platforms": [
      {
        "platform": "webtoon",
        "label": "WEBTOON",
        "read_url": "https://www.webtoons.com/en/action/the-regressed-mercenary-has-a-plan/list?title_no=7261"
      }
    ]
  },
  {
    "id": "surviving-the-game-as-a-barbarian",
    "title": "Surviving the Game as a Barbarian",
    "title_kr": "게임 속 바바리안으로 살아남기",
    "anilist_id": 164857,
    "platform": "webtoon",
    "platform_label": "WEBTOON",
    "read_url": "https://www.webtoons.com/en/fantasy/surviving-the-game-as-a-barbarian/list?title_no=5515",
    "update_day": 6,
    "update_day_name": "Saturday",
    "release_hour_kst": 11,
    "on_hiatus": false,
    "genre": "Fantasy",
    "tags": [
      "action",
      "adventure",
      "fantasy"
    ],
    "amazon_vol1": null,
    "seo_description": "Surviving the Game as a Barbarian drops every Saturday on WEBTOON. Live countdown to the next episode.",
    "platforms": [
      {
        "platform": "webtoon",
        "label": "WEBTOON",
        "read_url": "https://www.webtoons.com/en/fantasy/surviving-the-game-as-a-barbarian/list?title_no=5515"
      }
    ]
  },
  {
    "id": "operation-true-love",
    "title": "Operation: True Love",
    "title_kr": "작전명 순정",
    "anilist_id": 149483,
    "platform": "webtoon",
    "platform_label": "WEBTOON",
    "read_url": "https://www.webtoons.com/en/romance/operation-true-love/list?title_no=4465",
    "update_day": 5,
    "update_day_name": "Friday",
    "release_hour_kst": 11,
    "on_hiatus": false,
    "genre": "Romance",
    "tags": [
      "drama",
      "psychological",
      "romance"
    ],
    "amazon_vol1": null,
    "seo_description": "Operation: True Love drops every Friday on WEBTOON. Live countdown to the next episode.",
    "platforms": [
      {
        "platform": "webtoon",
        "label": "WEBTOON",
        "read_url": "https://www.webtoons.com/en/romance/operation-true-love/list?title_no=4465"
      }
    ]
  },
  {
    "id": "time-limited-genius-dark-knight",
    "title": "Time-Limited Genius Dark Knight",
    "title_kr": "시한부 천재 암흑기사",
    "anilist_id": 165182,
    "platform": "webtoon",
    "platform_label": "WEBTOON",
    "read_url": "https://www.webtoons.com/en/fantasy/time-limited-genius-dark-knight/list?title_no=5639",
    "update_day": 3,
    "update_day_name": "Wednesday",
    "release_hour_kst": 10,
    "on_hiatus": false,
    "genre": "Fantasy",
    "tags": [
      "action",
      "fantasy"
    ],
    "amazon_vol1": null,
    "seo_description": "Time-Limited Genius Dark Knight drops every Wednesday on WEBTOON. Live countdown to the next episode.",
    "platforms": [
      {
        "platform": "webtoon",
        "label": "WEBTOON",
        "read_url": "https://www.webtoons.com/en/fantasy/time-limited-genius-dark-knight/list?title_no=5639"
      }
    ]
  },
  {
    "id": "the-lone-necromancer",
    "title": "The Lone Necromancer",
    "title_kr": "나 혼자 네크로맨서",
    "anilist_id": 139572,
    "platform": "webtoon",
    "platform_label": "WEBTOON",
    "read_url": "https://www.webtoons.com/en/fantasy/the-lone-necromancer/list?title_no=3690",
    "update_day": 0,
    "update_day_name": "Sunday",
    "release_hour_kst": 11,
    "on_hiatus": false,
    "genre": "Fantasy",
    "tags": [
      "action",
      "fantasy"
    ],
    "amazon_vol1": null,
    "seo_description": "The Lone Necromancer drops every Sunday on WEBTOON. Live countdown to the next episode.",
    "platforms": [
      {
        "platform": "webtoon",
        "label": "WEBTOON",
        "read_url": "https://www.webtoons.com/en/fantasy/the-lone-necromancer/list?title_no=3690"
      }
    ]
  },
  {
    "id": "reality-quest",
    "title": "Reality Quest",
    "title_kr": "현실퀘스트",
    "anilist_id": 141705,
    "platform": "webtoon",
    "platform_label": "WEBTOON",
    "read_url": "https://www.webtoons.com/en/action/reality-quest/list?title_no=4697",
    "update_day": 1,
    "update_day_name": "Monday",
    "release_hour_kst": 12,
    "on_hiatus": false,
    "genre": "Supernatural",
    "tags": [
      "action",
      "supernatural"
    ],
    "amazon_vol1": null,
    "seo_description": "Reality Quest drops every Monday on WEBTOON. Live countdown to the next episode.",
    "platforms": [
      {
        "platform": "webtoon",
        "label": "WEBTOON",
        "read_url": "https://www.webtoons.com/en/action/reality-quest/list?title_no=4697"
      }
    ]
  },
  {
    "id": "hero-killer",
    "title": "Hero Killer",
    "title_kr": "히어로 킬러",
    "anilist_id": 132093,
    "platform": "webtoon",
    "platform_label": "WEBTOON",
    "read_url": "https://www.webtoons.com/en/action/hero-killer/list?title_no=2745",
    "update_day": 4,
    "update_day_name": "Thursday",
    "release_hour_kst": 10,
    "on_hiatus": false,
    "genre": "Supernatural",
    "tags": [
      "action",
      "drama",
      "supernatural"
    ],
    "amazon_vol1": null,
    "seo_description": "Hero Killer drops every Thursday on WEBTOON. Live countdown to the next episode.",
    "platforms": [
      {
        "platform": "webtoon",
        "label": "WEBTOON",
        "read_url": "https://www.webtoons.com/en/action/hero-killer/list?title_no=2745"
      }
    ]
  },
  {
    "id": "absolute-sword-sense",
    "title": "Absolute Sword Sense",
    "title_kr": "절대검감",
    "anilist_id": 151460,
    "platform": "webtoon",
    "platform_label": "WEBTOON",
    "read_url": "https://www.webtoons.com/en/action/absolute-sword-sense/list?title_no=5100",
    "update_day": 0,
    "update_day_name": "Sunday",
    "release_hour_kst": 11,
    "on_hiatus": false,
    "genre": "Fantasy",
    "tags": [
      "action",
      "fantasy"
    ],
    "amazon_vol1": null,
    "seo_description": "Absolute Sword Sense drops every Sunday on WEBTOON. Live countdown to the next episode.",
    "platforms": [
      {
        "platform": "webtoon",
        "label": "WEBTOON",
        "read_url": "https://www.webtoons.com/en/action/absolute-sword-sense/list?title_no=5100"
      }
    ]
  },
  {
    "id": "the-player-hides-his-past",
    "title": "The Player Hides His Past",
    "title_kr": "플레이어가 과거를 숨김",
    "anilist_id": 166154,
    "platform": "webtoon",
    "platform_label": "WEBTOON",
    "read_url": "https://www.webtoons.com/en/action/the-player-hides-his-past/list?title_no=5655",
    "update_day": 4,
    "update_day_name": "Thursday",
    "release_hour_kst": 11,
    "on_hiatus": false,
    "genre": "Fantasy",
    "tags": [
      "action",
      "fantasy"
    ],
    "amazon_vol1": null,
    "seo_description": "The Player Hides His Past drops every Thursday on WEBTOON. Live countdown to the next episode.",
    "platforms": [
      {
        "platform": "webtoon",
        "label": "WEBTOON",
        "read_url": "https://www.webtoons.com/en/action/the-player-hides-his-past/list?title_no=5655"
      }
    ]
  },
  {
    "id": "returned-by-the-king",
    "title": "Returned by the King",
    "title_kr": "왕의 힘으로 회귀한다",
    "anilist_id": 170724,
    "platform": "webtoon",
    "platform_label": "WEBTOON",
    "read_url": "https://www.webtoons.com/en/action/returned-by-the-king/list?title_no=6213",
    "update_day": 6,
    "update_day_name": "Saturday",
    "release_hour_kst": 11,
    "on_hiatus": false,
    "genre": "Drama",
    "tags": [
      "action",
      "drama",
      "fantasy"
    ],
    "amazon_vol1": null,
    "seo_description": "Returned by the King drops every Saturday on WEBTOON. Live countdown to the next episode.",
    "platforms": [
      {
        "platform": "webtoon",
        "label": "WEBTOON",
        "read_url": "https://www.webtoons.com/en/action/returned-by-the-king/list?title_no=6213"
      }
    ]
  },
  {
    "id": "absolute-regression",
    "title": "Absolute Regression",
    "title_kr": "절대회귀",
    "anilist_id": 180891,
    "platform": "webtoon",
    "platform_label": "WEBTOON",
    "read_url": "https://www.webtoons.com/en/fantasy/absolute-regression/list?title_no=7004",
    "update_day": 6,
    "update_day_name": "Saturday",
    "release_hour_kst": 11,
    "on_hiatus": false,
    "genre": "Fantasy",
    "tags": [
      "action",
      "fantasy"
    ],
    "amazon_vol1": null,
    "seo_description": "Absolute Regression drops every Saturday on WEBTOON. Live countdown to the next episode.",
    "platforms": [
      {
        "platform": "webtoon",
        "label": "WEBTOON",
        "read_url": "https://www.webtoons.com/en/fantasy/absolute-regression/list?title_no=7004"
      }
    ]
  },
  {
    "id": "my-bias-gets-on-the-last-train",
    "title": "My Bias Gets on the Last Train",
    "title_kr": "내 최애는 막차를 탄다",
    "anilist_id": 187944,
    "platform": "webtoon",
    "platform_label": "WEBTOON",
    "read_url": "https://www.webtoons.com/en/romance/my-bias-gets-on-the-last-train/list?title_no=7857",
    "update_day": 2,
    "update_day_name": "Tuesday",
    "release_hour_kst": 10,
    "on_hiatus": false,
    "genre": "Romance",
    "tags": [
      "drama",
      "romance"
    ],
    "amazon_vol1": null,
    "seo_description": "My Bias Gets on the Last Train drops every Tuesday on WEBTOON. Live countdown to the next episode.",
    "platforms": [
      {
        "platform": "webtoon",
        "label": "WEBTOON",
        "read_url": "https://www.webtoons.com/en/romance/my-bias-gets-on-the-last-train/list?title_no=7857"
      }
    ]
  },
  {
    "id": "chronicles-of-the-demon-faction",
    "title": "Chronicles of the Demon Faction",
    "title_kr": "마도전생기",
    "anilist_id": 164222,
    "platform": "webtoon",
    "platform_label": "WEBTOON",
    "read_url": "https://www.webtoons.com/en/action/chronicles-of-the-demon-faction/list?title_no=5832",
    "update_day": 5,
    "update_day_name": "Friday",
    "release_hour_kst": 11,
    "on_hiatus": false,
    "genre": "Fantasy",
    "tags": [
      "action",
      "fantasy"
    ],
    "amazon_vol1": null,
    "seo_description": "Chronicles of the Demon Faction drops every Friday on WEBTOON. Live countdown to the next episode.",
    "platforms": [
      {
        "platform": "webtoon",
        "label": "WEBTOON",
        "read_url": "https://www.webtoons.com/en/action/chronicles-of-the-demon-faction/list?title_no=5832"
      }
    ]
  },
  {
    "id": "killer-peter",
    "title": "Killer Peter",
    "title_kr": "킬러 배드로",
    "anilist_id": 170688,
    "platform": "webtoon",
    "platform_label": "WEBTOON",
    "read_url": "https://www.webtoons.com/en/action/killer-peter/list?title_no=5816",
    "update_day": 6,
    "update_day_name": "Saturday",
    "release_hour_kst": 11,
    "on_hiatus": false,
    "genre": "Comedy",
    "tags": [
      "action",
      "comedy",
      "drama"
    ],
    "amazon_vol1": null,
    "seo_description": "Killer Peter drops every Saturday on WEBTOON. Live countdown to the next episode.",
    "platforms": [
      {
        "platform": "webtoon",
        "label": "WEBTOON",
        "read_url": "https://www.webtoons.com/en/action/killer-peter/list?title_no=5816"
      }
    ]
  },
  {
    "id": "murim-rpg-simulation",
    "title": "Murim RPG Simulation",
    "title_kr": "천마육성",
    "anilist_id": 141076,
    "platform": "webtoon",
    "platform_label": "WEBTOON",
    "read_url": "https://www.webtoons.com/en/action/murim-rpg-simulation/list?title_no=3779",
    "update_day": 5,
    "update_day_name": "Friday",
    "release_hour_kst": 11,
    "on_hiatus": false,
    "genre": "Fantasy",
    "tags": [
      "action",
      "adventure",
      "fantasy"
    ],
    "amazon_vol1": null,
    "seo_description": "Murim RPG Simulation drops every Friday on WEBTOON. Live countdown to the next episode.",
    "platforms": [
      {
        "platform": "webtoon",
        "label": "WEBTOON",
        "read_url": "https://www.webtoons.com/en/action/murim-rpg-simulation/list?title_no=3779"
      }
    ]
  },
  {
    "id": "the-top-dungeon-farmer",
    "title": "The Top Dungeon Farmer",
    "title_kr": "나혼자 탑에서 농사",
    "anilist_id": 166658,
    "platform": "webtoon",
    "platform_label": "WEBTOON",
    "read_url": "https://www.webtoons.com/en/fantasy/the-top-dungeon-farmer/list?title_no=5656",
    "update_day": 4,
    "update_day_name": "Thursday",
    "release_hour_kst": 10,
    "on_hiatus": false,
    "genre": "Fantasy",
    "tags": [
      "fantasy"
    ],
    "amazon_vol1": null,
    "seo_description": "The Top Dungeon Farmer drops every Thursday on WEBTOON. Live countdown to the next episode.",
    "platforms": [
      {
        "platform": "webtoon",
        "label": "WEBTOON",
        "read_url": "https://www.webtoons.com/en/fantasy/the-top-dungeon-farmer/list?title_no=5656"
      }
    ]
  },
  {
    "id": "99-reinforced-wooden-stick",
    "title": "+99 Reinforced Wooden Stick",
    "title_kr": "99강화나무몽둥이",
    "anilist_id": 147102,
    "platform": "webtoon",
    "platform_label": "WEBTOON",
    "read_url": "https://www.webtoons.com/en/comedy/99-reinforced-wooden-stick/list?title_no=4286",
    "update_day": 6,
    "update_day_name": "Saturday",
    "release_hour_kst": 11,
    "on_hiatus": false,
    "genre": "Comedy",
    "tags": [
      "action",
      "adventure",
      "comedy",
      "fantasy"
    ],
    "amazon_vol1": null,
    "seo_description": "+99 Reinforced Wooden Stick drops every Saturday on WEBTOON. Live countdown to the next episode.",
    "platforms": [
      {
        "platform": "webtoon",
        "label": "WEBTOON",
        "read_url": "https://www.webtoons.com/en/comedy/99-reinforced-wooden-stick/list?title_no=4286"
      }
    ]
  },
  {
    "id": "the-constellations-are-my-disciples",
    "title": "The Constellations Are My Disciples",
    "title_kr": "성좌들이 내 제자",
    "anilist_id": 163448,
    "platform": "webtoon",
    "platform_label": "WEBTOON",
    "read_url": "https://www.webtoons.com/en/fantasy/the-constellations-are-my-disciples/list?title_no=5638",
    "update_day": 0,
    "update_day_name": "Sunday",
    "release_hour_kst": 11,
    "on_hiatus": false,
    "genre": "Fantasy",
    "tags": [
      "action",
      "fantasy"
    ],
    "amazon_vol1": null,
    "seo_description": "The Constellations Are My Disciples drops every Sunday on WEBTOON. Live countdown to the next episode.",
    "platforms": [
      {
        "platform": "webtoon",
        "label": "WEBTOON",
        "read_url": "https://www.webtoons.com/en/fantasy/the-constellations-are-my-disciples/list?title_no=5638"
      }
    ]
  },
  {
    "id": "enrolling-in-the-transcendent-academy",
    "title": "Enrolling in the Transcendent Academy",
    "title_kr": "초월자 학원의 수강생이 되었다",
    "anilist_id": 152608,
    "platform": "webtoon",
    "platform_label": "WEBTOON",
    "read_url": "https://www.webtoons.com/en/fantasy/enrolling-in-the-transcendent-academy/list?title_no=5420",
    "update_day": 6,
    "update_day_name": "Saturday",
    "release_hour_kst": 11,
    "on_hiatus": false,
    "genre": "Fantasy",
    "tags": [
      "action",
      "adventure",
      "fantasy"
    ],
    "amazon_vol1": null,
    "seo_description": "Enrolling in the Transcendent Academy drops every Saturday on WEBTOON. Live countdown to the next episode.",
    "platforms": [
      {
        "platform": "webtoon",
        "label": "WEBTOON",
        "read_url": "https://www.webtoons.com/en/fantasy/enrolling-in-the-transcendent-academy/list?title_no=5420"
      }
    ]
  },
  {
    "id": "infinite-leveling-murim",
    "title": "Infinite Leveling: Murim",
    "title_kr": "무한 레벨업 in 무림",
    "anilist_id": 134635,
    "platform": "webtoon",
    "platform_label": "WEBTOON",
    "read_url": "https://www.webtoons.com/en/action/infinite-leveling-murim/list?title_no=2676",
    "update_day": 3,
    "update_day_name": "Wednesday",
    "release_hour_kst": 11,
    "on_hiatus": false,
    "genre": "Comedy",
    "tags": [
      "action",
      "adventure",
      "comedy",
      "fantasy"
    ],
    "amazon_vol1": null,
    "seo_description": "Infinite Leveling: Murim drops every Wednesday on WEBTOON. Live countdown to the next episode.",
    "platforms": [
      {
        "platform": "webtoon",
        "label": "WEBTOON",
        "read_url": "https://www.webtoons.com/en/action/infinite-leveling-murim/list?title_no=2676"
      }
    ]
  },
  {
    "id": "villains-are-destined-to-die",
    "title": "Villains Are Destined to Die",
    "title_kr": null,
    "anilist_id": 118408,
    "platform": "tapas",
    "platform_label": "TAPAS",
    "read_url": "https://tapas.io/series/villains-are-destined-to-die/info",
    "update_day": null,
    "update_day_name": null,
    "release_hour_kst": 0,
    "on_hiatus": false,
    "genre": "Romance",
    "tags": [
      "romance"
    ],
    "amazon_vol1": null,
    "seo_description": "Villains Are Destined to Die releases on Tapas. Live countdown to the next episode.",
    "platforms": [
      {
        "platform": "tapas",
        "label": "TAPAS",
        "read_url": "https://tapas.io/series/villains-are-destined-to-die/info"
      }
    ]
  },
  {
    "id": "latna-saga-survival-of-a-sword-king",
    "title": "Latna Saga: Survival of a Sword King",
    "title_kr": null,
    "anilist_id": 114605,
    "platform": "tapas",
    "platform_label": "TAPAS",
    "read_url": "https://tapas.io/series/latna-saga-survival-of-a-sword-king/info",
    "update_day": null,
    "update_day_name": null,
    "release_hour_kst": 0,
    "on_hiatus": false,
    "genre": "Fantasy",
    "tags": [
      "fantasy"
    ],
    "amazon_vol1": null,
    "seo_description": "Latna Saga: Survival of a Sword King releases on Tapas. Live countdown to the next episode.",
    "platforms": [
      {
        "platform": "tapas",
        "label": "TAPAS",
        "read_url": "https://tapas.io/series/latna-saga-survival-of-a-sword-king/info"
      }
    ]
  },
  {
    "id": "the-sss-ranker-returns",
    "title": "The SSS-Ranker Returns",
    "title_kr": null,
    "anilist_id": 153883,
    "platform": "tapas",
    "platform_label": "TAPAS",
    "read_url": "https://tapas.io/series/the-sss-ranker-returns/info",
    "update_day": null,
    "update_day_name": null,
    "release_hour_kst": 0,
    "on_hiatus": false,
    "genre": "Action",
    "tags": [
      "action"
    ],
    "amazon_vol1": null,
    "seo_description": "The SSS-Ranker Returns releases on Tapas. Live countdown to the next episode.",
    "platforms": [
      {
        "platform": "tapas",
        "label": "TAPAS",
        "read_url": "https://tapas.io/series/the-sss-ranker-returns/info"
      }
    ]
  },
  {
    "id": "the-archmage-returns-after-4000-years",
    "title": "The Archmage Returns After 4000 Years",
    "title_kr": null,
    "anilist_id": 118424,
    "platform": "tapas",
    "platform_label": "TAPAS",
    "read_url": "https://tapas.io/series/the-archmage-returns-after-4000-years/info",
    "update_day": null,
    "update_day_name": null,
    "release_hour_kst": 0,
    "on_hiatus": false,
    "genre": "Fantasy",
    "tags": [
      "fantasy"
    ],
    "amazon_vol1": null,
    "seo_description": "The Archmage Returns After 4000 Years releases on Tapas. Live countdown to the next episode.",
    "platforms": [
      {
        "platform": "tapas",
        "label": "TAPAS",
        "read_url": "https://tapas.io/series/the-archmage-returns-after-4000-years/info"
      }
    ]
  },
  {
    "id": "the-max-level-hero-strikes-back",
    "title": "The Max Level Hero Strikes Back",
    "title_kr": null,
    "anilist_id": 125636,
    "platform": "tapas",
    "platform_label": "TAPAS",
    "read_url": "https://tapas.io/series/the-max-level-hero-strikes-back/info",
    "update_day": null,
    "update_day_name": null,
    "release_hour_kst": 0,
    "on_hiatus": false,
    "genre": "Fantasy",
    "tags": [
      "fantasy"
    ],
    "amazon_vol1": null,
    "seo_description": "The Max Level Hero Strikes Back releases on Tapas. Live countdown to the next episode.",
    "platforms": [
      {
        "platform": "tapas",
        "label": "TAPAS",
        "read_url": "https://tapas.io/series/the-max-level-hero-strikes-back/info"
      }
    ]
  },
  {
    "id": "the-legendary-spearman-returns",
    "title": "The Legendary Spearman Returns",
    "title_kr": null,
    "anilist_id": 141479,
    "platform": "tapas",
    "platform_label": "TAPAS",
    "read_url": "https://tapas.io/series/the-legendary-spearman-returns/info",
    "update_day": null,
    "update_day_name": null,
    "release_hour_kst": 0,
    "on_hiatus": false,
    "genre": "Action",
    "tags": [
      "action"
    ],
    "amazon_vol1": null,
    "seo_description": "The Legendary Spearman Returns releases on Tapas. Live countdown to the next episode.",
    "platforms": [
      {
        "platform": "tapas",
        "label": "TAPAS",
        "read_url": "https://tapas.io/series/the-legendary-spearman-returns/info"
      }
    ]
  },
  {
    "id": "ranker-s-return",
    "title": "Ranker's Return",
    "title_kr": null,
    "anilist_id": 137969,
    "platform": "tapas",
    "platform_label": "TAPAS",
    "read_url": "https://tapas.io/series/rankers-return/info",
    "update_day": null,
    "update_day_name": null,
    "release_hour_kst": 0,
    "on_hiatus": false,
    "genre": "Action",
    "tags": [
      "action"
    ],
    "amazon_vol1": null,
    "seo_description": "Ranker's Return releases on Tapas. Live countdown to the next episode.",
    "platforms": [
      {
        "platform": "tapas",
        "label": "TAPAS",
        "read_url": "https://tapas.io/series/rankers-return/info"
      }
    ]
  },
  {
    "id": "i-am-the-real-one",
    "title": "I Am the Real One",
    "title_kr": null,
    "anilist_id": 124783,
    "platform": "tapas",
    "platform_label": "TAPAS",
    "read_url": "https://tapas.io/series/i-am-the-real-one/info",
    "update_day": null,
    "update_day_name": null,
    "release_hour_kst": 0,
    "on_hiatus": false,
    "genre": "Romance",
    "tags": [
      "romance"
    ],
    "amazon_vol1": null,
    "seo_description": "I Am the Real One releases on Tapas. Live countdown to the next episode.",
    "platforms": [
      {
        "platform": "tapas",
        "label": "TAPAS",
        "read_url": "https://tapas.io/series/i-am-the-real-one/info"
      }
    ]
  },
  {
    "id": "semantic-error",
    "title": "Semantic Error",
    "title_kr": null,
    "anilist_id": 125167,
    "platform": "tapas",
    "platform_label": "TAPAS",
    "read_url": "https://tapas.io/series/semantic-error/info",
    "update_day": null,
    "update_day_name": null,
    "release_hour_kst": 0,
    "on_hiatus": false,
    "genre": "Romance",
    "tags": [
      "romance"
    ],
    "amazon_vol1": null,
    "seo_description": "Semantic Error releases on Tapas. Live countdown to the next episode.",
    "platforms": [
      {
        "platform": "tapas",
        "label": "TAPAS",
        "read_url": "https://tapas.io/series/semantic-error/info"
      }
    ]
  },
  {
    "id": "the-male-lead-s-little-lion-daughter",
    "title": "The Male Lead's Little Lion Daughter",
    "title_kr": null,
    "anilist_id": 138363,
    "platform": "tapas",
    "platform_label": "TAPAS",
    "read_url": "https://tapas.io/series/the-male-leads-little-lion-daughter/info",
    "update_day": null,
    "update_day_name": null,
    "release_hour_kst": 0,
    "on_hiatus": false,
    "genre": "Romance",
    "tags": [
      "romance"
    ],
    "amazon_vol1": null,
    "seo_description": "The Male Lead's Little Lion Daughter releases on Tapas. Live countdown to the next episode.",
    "platforms": [
      {
        "platform": "tapas",
        "label": "TAPAS",
        "read_url": "https://tapas.io/series/the-male-leads-little-lion-daughter/info"
      }
    ]
  },
  {
    "id": "not-sew-wicked-stepmom",
    "title": "Not-Sew-Wicked Stepmom",
    "title_kr": null,
    "anilist_id": 132359,
    "platform": "tapas",
    "platform_label": "TAPAS",
    "read_url": "https://tapas.io/series/not-sew-wicked-stepmom/info",
    "update_day": null,
    "update_day_name": null,
    "release_hour_kst": 0,
    "on_hiatus": false,
    "genre": "Romance",
    "tags": [
      "romance"
    ],
    "amazon_vol1": null,
    "seo_description": "Not-Sew-Wicked Stepmom releases on Tapas. Live countdown to the next episode.",
    "platforms": [
      {
        "platform": "tapas",
        "label": "TAPAS",
        "read_url": "https://tapas.io/series/not-sew-wicked-stepmom/info"
      }
    ]
  },
  {
    "id": "beware-the-villainess",
    "title": "Beware the Villainess!",
    "title_kr": null,
    "anilist_id": 117540,
    "platform": "tapas",
    "platform_label": "TAPAS",
    "read_url": "https://tapas.io/series/beware-the-villainess/info",
    "update_day": null,
    "update_day_name": null,
    "release_hour_kst": 0,
    "on_hiatus": false,
    "genre": "Romance",
    "tags": [
      "romance"
    ],
    "amazon_vol1": null,
    "seo_description": "Beware the Villainess! releases on Tapas. Live countdown to the next episode.",
    "platforms": [
      {
        "platform": "tapas",
        "label": "TAPAS",
        "read_url": "https://tapas.io/series/beware-the-villainess/info"
      }
    ]
  },
  {
    "id": "my-life-as-an-internet-novel",
    "title": "My Life as an Internet Novel",
    "title_kr": null,
    "anilist_id": 110059,
    "platform": "tapas",
    "platform_label": "TAPAS",
    "read_url": "https://tapas.io/series/my-life-as-an-internet-novel/info",
    "update_day": null,
    "update_day_name": null,
    "release_hour_kst": 0,
    "on_hiatus": false,
    "genre": "Romance",
    "tags": [
      "romance"
    ],
    "amazon_vol1": null,
    "seo_description": "My Life as an Internet Novel releases on Tapas. Live countdown to the next episode.",
    "platforms": [
      {
        "platform": "tapas",
        "label": "TAPAS",
        "read_url": "https://tapas.io/series/my-life-as-an-internet-novel/info"
      }
    ]
  },
  {
    "id": "doctor-live-again",
    "title": "Doctor, Live Again",
    "title_kr": null,
    "anilist_id": 129579,
    "platform": "tapas",
    "platform_label": "TAPAS",
    "read_url": "https://tapas.io/series/doctor-live-again/info",
    "update_day": null,
    "update_day_name": null,
    "release_hour_kst": 0,
    "on_hiatus": false,
    "genre": "Drama",
    "tags": [
      "drama"
    ],
    "amazon_vol1": null,
    "seo_description": "Doctor, Live Again releases on Tapas. Live countdown to the next episode.",
    "platforms": [
      {
        "platform": "tapas",
        "label": "TAPAS",
        "read_url": "https://tapas.io/series/doctor-live-again/info"
      }
    ]
  },
  {
    "id": "author-of-my-own-destiny",
    "title": "Author of My Own Destiny",
    "title_kr": null,
    "anilist_id": 138655,
    "platform": "tapas",
    "platform_label": "TAPAS",
    "read_url": "https://tapas.io/series/author-of-my-own-destiny/info",
    "update_day": null,
    "update_day_name": null,
    "release_hour_kst": 0,
    "on_hiatus": false,
    "genre": "Romance",
    "tags": [
      "romance"
    ],
    "amazon_vol1": null,
    "seo_description": "Author of My Own Destiny releases on Tapas. Live countdown to the next episode.",
    "platforms": [
      {
        "platform": "tapas",
        "label": "TAPAS",
        "read_url": "https://tapas.io/series/author-of-my-own-destiny/info"
      }
    ]
  },
  {
    "id": "pick-me-up",
    "title": "Pick Me Up",
    "title_kr": null,
    "anilist_id": 159441,
    "platform": "mangaplus",
    "platform_label": "MANGA PLUS",
    "read_url": "https://anilist.co/manga/159441",
    "update_day": null,
    "update_day_name": null,
    "release_hour_kst": 0,
    "on_hiatus": false,
    "genre": "Action",
    "tags": [
      "action"
    ],
    "amazon_vol1": null,
    "seo_description": "Pick Me Up releases on MANGA PLUS. Live countdown to the next episode.",
    "platforms": [
      {
        "platform": "mangaplus",
        "label": "MANGA PLUS",
        "read_url": "https://anilist.co/manga/159441"
      }
    ]
  },
  {
    "id": "the-infinite-mage",
    "title": "The Infinite Mage",
    "title_kr": null,
    "anilist_id": 159930,
    "platform": "mangaplus",
    "platform_label": "MANGA PLUS",
    "read_url": "https://anilist.co/manga/159930",
    "update_day": null,
    "update_day_name": null,
    "release_hour_kst": 0,
    "on_hiatus": false,
    "genre": "Fantasy",
    "tags": [
      "fantasy"
    ],
    "amazon_vol1": null,
    "seo_description": "The Infinite Mage releases on MANGA PLUS. Live countdown to the next episode.",
    "platforms": [
      {
        "platform": "mangaplus",
        "label": "MANGA PLUS",
        "read_url": "https://anilist.co/manga/159930"
      }
    ]
  },
  {
    "id": "god-of-blackfield",
    "title": "God of Blackfield",
    "title_kr": null,
    "anilist_id": 118267,
    "platform": "mangaplus",
    "platform_label": "MANGA PLUS",
    "read_url": "https://anilist.co/manga/118267",
    "update_day": null,
    "update_day_name": null,
    "release_hour_kst": 0,
    "on_hiatus": false,
    "genre": "Action",
    "tags": [
      "action"
    ],
    "amazon_vol1": null,
    "seo_description": "God of Blackfield releases on MANGA PLUS. Live countdown to the next episode.",
    "platforms": [
      {
        "platform": "mangaplus",
        "label": "MANGA PLUS",
        "read_url": "https://anilist.co/manga/118267"
      }
    ]
  },
  {
    "id": "player",
    "title": "Player",
    "title_kr": null,
    "anilist_id": 119363,
    "platform": "mangaplus",
    "platform_label": "MANGA PLUS",
    "read_url": "https://anilist.co/manga/119363",
    "update_day": null,
    "update_day_name": null,
    "release_hour_kst": 0,
    "on_hiatus": false,
    "genre": "Action",
    "tags": [
      "action"
    ],
    "amazon_vol1": null,
    "seo_description": "Player releases on MANGA PLUS. Live countdown to the next episode.",
    "platforms": [
      {
        "platform": "mangaplus",
        "label": "MANGA PLUS",
        "read_url": "https://anilist.co/manga/119363"
      }
    ]
  },
  {
    "id": "tyrant-of-the-tower-defense-game",
    "title": "Tyrant of the Tower Defense Game",
    "title_kr": null,
    "anilist_id": 153513,
    "platform": "mangaplus",
    "platform_label": "MANGA PLUS",
    "read_url": "https://anilist.co/manga/153513",
    "update_day": null,
    "update_day_name": null,
    "release_hour_kst": 0,
    "on_hiatus": false,
    "genre": "Fantasy",
    "tags": [
      "fantasy"
    ],
    "amazon_vol1": null,
    "seo_description": "Tyrant of the Tower Defense Game releases on MANGA PLUS. Live countdown to the next episode.",
    "platforms": [
      {
        "platform": "mangaplus",
        "label": "MANGA PLUS",
        "read_url": "https://anilist.co/manga/153513"
      }
    ]
  }
]